{
    "DataRailConsistent":  true,
    "SynchronizationStatus":  "FULLY SYNCED",
    "TotalEnrichedLeads":  50,
    "AllOrganPayloadsIntact":  true,
    "ProposalsGenerated":  8,
    "Dispatched":  3,
    "LatestSentFolder":  "G:\\My Drive\\Sovereign_Monad_Ecosystem\\agents\\monad-mev\\outreach\\sent\\batch-2026-05-09-03-41-total-standard-DISPATCHED-2026-05-09-03-42",
    "LatestBatch":  "G:\\My Drive\\Sovereign_Monad_Ecosystem\\agents\\monad-mev\\proposals\\batch-2026-05-13-22-20",
    "Timestamp":  {
                      "value":  "\/Date(1778751387890)\/",
                      "DisplayHint":  2,
                      "DateTime":  "Thursday, May 14, 2026 4:36:27 AM"
                  }
}
